{"trial_id": "17", "hyperparameters": {"space": [{"class_name": "Int", "config": {"name": "input_units", "default": null, "conditions": [], "min_value": 32, "max_value": 512, "step": 32, "sampling": "linear"}}, {"class_name": "Choice", "config": {"name": "input_activation", "default": "relu", "conditions": [], "values": ["relu", "tanh", "sigmoid"], "ordered": false}}, {"class_name": "Float", "config": {"name": "input_l2", "default": 0.001, "conditions": [], "min_value": 0.001, "max_value": 0.1, "step": 0.001, "sampling": "linear"}}, {"class_name": "Float", "config": {"name": "input_dropout", "default": 0.0, "conditions": [], "min_value": 0.0, "max_value": 0.5, "step": 0.05, "sampling": "linear"}}, {"class_name": "Int", "config": {"name": "num_layers", "default": null, "conditions": [], "min_value": 1, "max_value": 5, "step": 1, "sampling": "linear"}}, {"class_name": "Int", "config": {"name": "hidden_units_0", "default": null, "conditions": [], "min_value": 32, "max_value": 512, "step": 32, "sampling": "linear"}}, {"class_name": "Choice", "config": {"name": "hidden_activation_0", "default": "relu", "conditions": [], "values": ["relu", "tanh", "sigmoid"], "ordered": false}}, {"class_name": "Float", "config": {"name": "hidden_l2_0", "default": 0.001, "conditions": [], "min_value": 0.001, "max_value": 0.1, "step": 0.001, "sampling": "linear"}}, {"class_name": "Float", "config": {"name": "hidden_dropout_0", "default": 0.0, "conditions": [], "min_value": 0.0, "max_value": 0.5, "step": 0.05, "sampling": "linear"}}, {"class_name": "Choice", "config": {"name": "learning_rate", "default": 0.01, "conditions": [], "values": [0.01, 0.001, 0.0001], "ordered": true}}, {"class_name": "Int", "config": {"name": "hidden_units_1", "default": null, "conditions": [], "min_value": 32, "max_value": 512, "step": 32, "sampling": "linear"}}, {"class_name": "Choice", "config": {"name": "hidden_activation_1", "default": "relu", "conditions": [], "values": ["relu", "tanh", "sigmoid"], "ordered": false}}, {"class_name": "Float", "config": {"name": "hidden_l2_1", "default": 0.001, "conditions": [], "min_value": 0.001, "max_value": 0.1, "step": 0.001, "sampling": "linear"}}, {"class_name": "Float", "config": {"name": "hidden_dropout_1", "default": 0.0, "conditions": [], "min_value": 0.0, "max_value": 0.5, "step": 0.05, "sampling": "linear"}}, {"class_name": "Int", "config": {"name": "hidden_units_2", "default": null, "conditions": [], "min_value": 32, "max_value": 512, "step": 32, "sampling": "linear"}}, {"class_name": "Choice", "config": {"name": "hidden_activation_2", "default": "relu", "conditions": [], "values": ["relu", "tanh", "sigmoid"], "ordered": false}}, {"class_name": "Float", "config": {"name": "hidden_l2_2", "default": 0.001, "conditions": [], "min_value": 0.001, "max_value": 0.1, "step": 0.001, "sampling": "linear"}}, {"class_name": "Float", "config": {"name": "hidden_dropout_2", "default": 0.0, "conditions": [], "min_value": 0.0, "max_value": 0.5, "step": 0.05, "sampling": "linear"}}, {"class_name": "Int", "config": {"name": "hidden_units_3", "default": null, "conditions": [], "min_value": 32, "max_value": 512, "step": 32, "sampling": "linear"}}, {"class_name": "Choice", "config": {"name": "hidden_activation_3", "default": "relu", "conditions": [], "values": ["relu", "tanh", "sigmoid"], "ordered": false}}, {"class_name": "Float", "config": {"name": "hidden_l2_3", "default": 0.001, "conditions": [], "min_value": 0.001, "max_value": 0.1, "step": 0.001, "sampling": "linear"}}, {"class_name": "Float", "config": {"name": "hidden_dropout_3", "default": 0.0, "conditions": [], "min_value": 0.0, "max_value": 0.5, "step": 0.05, "sampling": "linear"}}, {"class_name": "Int", "config": {"name": "hidden_units_4", "default": null, "conditions": [], "min_value": 32, "max_value": 512, "step": 32, "sampling": "linear"}}, {"class_name": "Choice", "config": {"name": "hidden_activation_4", "default": "relu", "conditions": [], "values": ["relu", "tanh", "sigmoid"], "ordered": false}}, {"class_name": "Float", "config": {"name": "hidden_l2_4", "default": 0.001, "conditions": [], "min_value": 0.001, "max_value": 0.1, "step": 0.001, "sampling": "linear"}}, {"class_name": "Float", "config": {"name": "hidden_dropout_4", "default": 0.0, "conditions": [], "min_value": 0.0, "max_value": 0.5, "step": 0.05, "sampling": "linear"}}], "values": {"input_units": 224, "input_activation": "relu", "input_l2": 0.012, "input_dropout": 0.0, "num_layers": 1, "hidden_units_0": 320, "hidden_activation_0": "tanh", "hidden_l2_0": 0.007, "hidden_dropout_0": 0.30000000000000004, "learning_rate": 0.001, "hidden_units_1": 448, "hidden_activation_1": "sigmoid", "hidden_l2_1": 0.094, "hidden_dropout_1": 0.2, "hidden_units_2": 512, "hidden_activation_2": "sigmoid", "hidden_l2_2": 0.075, "hidden_dropout_2": 0.1, "hidden_units_3": 384, "hidden_activation_3": "tanh", "hidden_l2_3": 0.074, "hidden_dropout_3": 0.15000000000000002, "hidden_units_4": 32, "hidden_activation_4": "sigmoid", "hidden_l2_4": 0.008, "hidden_dropout_4": 0.30000000000000004}}, "metrics": {"metrics": {"loss": {"direction": "min", "observations": [{"value": [1.172621250152588], "step": 0}]}, "accuracy": {"direction": "max", "observations": [{"value": [0.661346435546875], "step": 0}]}, "val_loss": {"direction": "min", "observations": [{"value": [0.7625683546066284], "step": 0}]}, "val_accuracy": {"direction": "max", "observations": [{"value": [0.7202495336532593], "step": 0}]}}}, "score": 0.7202495336532593, "best_step": 0, "status": "COMPLETED", "message": null}